README.txt
setup.py
coin/__init__.py
coin/coin.py
coin/test/__init__.py
coin/test/test_coin.py
stochasticity.egg-info/PKG-INFO
stochasticity.egg-info/SOURCES.txt
stochasticity.egg-info/dependency_links.txt
stochasticity.egg-info/top_level.txt