Metadata-Version: 1.0
Name: stochasticity
Version: 0.1.2
Summary: Modules to generate various sorts of randomness, starting with a simple coin flip
Home-page: https://github.com/jeffwhite-619/stochasticity
Author: Jeff White
Author-email: thisguy@thejeffwhite.com
License: GNU GPLv3
Platform: UNKNOWN
